{"0":{"GMT_schedule":"2021-01-24T14:30:18.0000000Z","EST_schedule":"2021-01-24 09:30:18","h_team":"FC Schalke 04","a_team":"Bayern Munich","m_h_odds":"+4500","m_a_odds":"-1430","m_t_odds":"+1050","league_name":"Bundesliga","m_h_improb":0.0217391304,"m_t_improb":0.0869565217,"m_a_improb":0.9346405229,"m_h_dodds":46.0,"m_t_dodds":11.5,"m_a_dodds":1.0699300699,"m_h_prob":0.0106418894,"m_t_prob":0.0844713476,"m_a_prob":0.904886763,"m_h_er":-0.510473086,"m_t_er":-0.0285795027,"m_a_er":-0.0318344424,"m_tqe_pick":"tie"},"1":{"GMT_schedule":"2021-01-24T17:00:00.0000000Z","EST_schedule":"2021-01-24 12:00:00","h_team":"TSG Hoffenheim","a_team":"1. FC K\u00f6ln","m_h_odds":"-124","m_a_odds":"+340","m_t_odds":"+265","league_name":"Bundesliga","m_h_improb":0.5535714286,"m_t_improb":0.2739726027,"m_a_improb":0.2272727273,"m_h_dodds":1.8064516129,"m_t_dodds":3.65,"m_a_dodds":4.4,"m_h_prob":0.5552128195,"m_t_prob":0.2588891527,"m_a_prob":0.1858980278,"m_h_er":0.0029650932,"m_t_er":-0.0550545926,"m_a_er":-0.1820486776,"m_tqe_pick":"home"},"2":{"GMT_schedule":"2021-01-29T19:30:00.0000000Z","EST_schedule":"2021-01-29 14:30:00","h_team":"VfB Stuttgart","a_team":"Mainz 05","m_h_odds":"-155","m_a_odds":"+380","m_t_odds":"+325","league_name":"Bundesliga","m_h_improb":0.6078431373,"m_t_improb":0.2352941176,"m_a_improb":0.2083333333,"m_h_dodds":1.6451612903,"m_t_dodds":4.25,"m_a_dodds":4.8,"m_h_prob":0.6018927052,"m_t_prob":0.2291580058,"m_a_prob":0.168949289,"m_h_er":-0.0097894205,"m_t_er":-0.0260784752,"m_a_er":-0.1890434129,"m_tqe_pick":"home"},"3":{"GMT_schedule":"2021-01-30T14:30:00.0000000Z","EST_schedule":"2021-01-30 09:30:00","h_team":"1. FC Union Berlin","a_team":"Borussia M\u00f6nchengladbach","m_h_odds":"+200","m_a_odds":"+125","m_t_odds":"+265","league_name":"Bundesliga","m_h_improb":0.3333333333,"m_t_improb":0.2739726027,"m_a_improb":0.4444444444,"m_h_dodds":3.0,"m_t_dodds":3.65,"m_a_dodds":2.25,"m_h_prob":0.3117345777,"m_t_prob":0.2490996392,"m_a_prob":0.439165783,"m_h_er":-0.0647962668,"m_t_er":-0.0907863168,"m_a_er":-0.0118769882,"m_tqe_pick":"away"},"4":{"GMT_schedule":"2021-01-30T14:30:00.0000000Z","EST_schedule":"2021-01-30 09:30:00","h_team":"Bayern Munich","a_team":"TSG Hoffenheim","m_h_odds":"-455","m_a_odds":"+1000","m_t_odds":"+620","league_name":"Bundesliga","m_h_improb":0.8198198198,"m_t_improb":0.1388888889,"m_a_improb":0.0909090909,"m_h_dodds":1.2197802198,"m_t_dodds":7.2,"m_a_dodds":11.0,"m_h_prob":0.7958376977,"m_t_prob":0.1430379956,"m_a_prob":0.0611243067,"m_h_er":-0.0292529181,"m_t_er":0.0298735682,"m_a_er":-0.3276326265,"m_tqe_pick":"tie"},"5":{"GMT_schedule":"2021-01-30T14:30:00.0000000Z","EST_schedule":"2021-01-30 09:30:00","h_team":"Borussia Dortmund","a_team":"FC Augsburg","m_h_odds":"-435","m_a_odds":"+1150","m_t_odds":"+535","league_name":"Bundesliga","m_h_improb":0.8130841121,"m_t_improb":0.157480315,"m_a_improb":0.08,"m_h_dodds":1.2298850575,"m_t_dodds":6.35,"m_a_dodds":12.5,"m_h_prob":0.7855908897,"m_t_prob":0.1617215842,"m_a_prob":0.0526875261,"m_h_er":-0.0338135034,"m_t_er":0.0269320597,"m_a_er":-0.3414059243,"m_tqe_pick":"tie"},"6":{"GMT_schedule":"2021-01-30T14:30:00.0000000Z","EST_schedule":"2021-01-30 09:30:00","h_team":"Eintracht Frankfurt","a_team":"Hertha BSC","m_h_odds":"-139","m_a_odds":"+325","m_t_odds":"+325","league_name":"Bundesliga","m_h_improb":0.5815899582,"m_t_improb":0.2352941176,"m_a_improb":0.2352941176,"m_h_dodds":1.7194244604,"m_t_dodds":4.25,"m_a_dodds":4.25,"m_h_prob":0.5773665211,"m_t_prob":0.2248766426,"m_a_prob":0.1977568364,"m_h_er":-0.007261881,"m_t_er":-0.0442742692,"m_a_er":-0.1595334455,"m_tqe_pick":"home"},"7":{"GMT_schedule":"2021-01-30T14:30:00.0000000Z","EST_schedule":"2021-01-30 09:30:00","h_team":"Werder Bremen","a_team":"FC Schalke 04","m_h_odds":"-109","m_a_odds":"+295","m_t_odds":"+255","league_name":"Bundesliga","m_h_improb":0.5215311005,"m_t_improb":0.2816901408,"m_a_improb":0.253164557,"m_h_dodds":1.9174311927,"m_t_dodds":3.55,"m_a_dodds":3.95,"m_h_prob":0.5247837965,"m_t_prob":0.2614823335,"m_a_prob":0.21373387,"m_h_er":0.0062368208,"m_t_er":-0.0717377161,"m_a_er":-0.1557512134,"m_tqe_pick":"home"},"8":{"GMT_schedule":"2021-01-30T17:30:00.0000000Z","EST_schedule":"2021-01-30 12:30:00","h_team":"RB Leipzig","a_team":"Bayer Leverkusen","m_h_odds":"-118","m_a_odds":"+285","m_t_odds":"+295","league_name":"Bundesliga","m_h_improb":0.5412844037,"m_t_improb":0.253164557,"m_a_improb":0.2597402597,"m_h_dodds":1.8474576271,"m_t_dodds":3.95,"m_a_dodds":3.85,"m_h_prob":0.5407368776,"m_t_prob":0.2362253882,"m_a_prob":0.2230377341,"m_h_er":-0.0010115312,"m_t_er":-0.0669097165,"m_a_er":-0.1413047236,"m_tqe_pick":"home"},"9":{"GMT_schedule":"2021-01-31T14:30:00.0000000Z","EST_schedule":"2021-01-31 09:30:00","h_team":"1. FC K\u00f6ln","a_team":"Arminia Bielefeld","m_h_odds":"+105","m_a_odds":"+285","m_t_odds":"+230","league_name":"Bundesliga","m_h_improb":0.487804878,"m_t_improb":0.303030303,"m_a_improb":0.2597402597,"m_h_dodds":2.05,"m_t_dodds":3.3,"m_a_dodds":3.85,"m_h_prob":0.4977106808,"m_t_prob":0.2807963128,"m_a_prob":0.2214930064,"m_h_er":0.0203068956,"m_t_er":-0.0733721677,"m_a_er":-0.1472519255,"m_tqe_pick":"home"},"10":{"GMT_schedule":"2021-01-31T17:00:00.0000000Z","EST_schedule":"2021-01-31 12:00:00","h_team":"VfL Wolfsburg","a_team":"SC Freiburg","m_h_odds":"-112","m_a_odds":"+295","m_t_odds":"+270","league_name":"Bundesliga","m_h_improb":0.5283018868,"m_t_improb":0.2702702703,"m_a_improb":0.253164557,"m_h_dodds":1.8928571429,"m_t_dodds":3.7,"m_a_dodds":3.95,"m_h_prob":0.5326164679,"m_t_prob":0.252376335,"m_a_prob":0.2150071971,"m_h_er":0.0081668857,"m_t_er":-0.0662075607,"m_a_er":-0.1507215713,"m_tqe_pick":"home"}}