{"0":{"GMT_schedule":"2021-05-07T23:00:00.0000000Z","EST_schedule":"2021-05-07 18:00:00","name":"Detroit Red Wings @ Columbus Blue Jackets","h_team":"CBJ Blue Jackets","a_team":"DET Red Wings","m_h_odds":"-148","m_a_odds":"+128","s_a_line":"+1.5","s_h_odds":"+180","s_a_odds":"-220","t_line":5.0,"t_o_odds":"-137","t_u_odds":"+114","league_name":"NHL","s_h_line":"-1.5","m_h_improb":0.5967741935,"m_a_improb":0.4385964912,"s_h_improb":0.3571428571,"s_a_improb":0.6875,"t_o_improb":0.5780590717,"t_u_improb":0.4672897196,"m_h_dodds":1.6756756757,"m_a_dodds":2.28,"s_h_dodds":2.8,"s_a_dodds":1.4545454545,"t_o_dodds":1.7299270073,"t_u_dodds":2.14,"s_a_pred":0.3080064376,"t_pred":9.7125722728,"m_h_prob":0.5122857365,"m_a_prob":0.4877142635,"s_h_prob":0.4525587083,"s_a_prob":0.5474412917,"t_o_prob":0.6469153459,"t_u_prob":0.3530846541,"m_h_er":-0.1415752524,"m_a_er":0.1119885208,"s_h_er":0.2671643833,"s_a_er":-0.2037217576,"t_o_er":0.1191163284,"t_u_er":-0.2443988403,"m_tqe_pick":"away","s_tqe_pick":"home","t_tqe_pick":"over","m_tqe_prob":0.4877142635,"s_tqe_prob":0.4525587083,"t_tqe_prob":0.6469153459,"m_tqe_er":0.1119885208,"s_tqe_er":0.2671643833,"t_tqe_er":0.1191163284},"1":{"GMT_schedule":"2021-05-07T23:00:00.0000000Z","EST_schedule":"2021-05-07 18:00:00","name":"Dallas Stars @ Tampa Bay Lightning","h_team":"TB Lightning","a_team":"DAL Stars","m_h_odds":"-157","m_a_odds":"+133","s_a_line":"+1.5","s_h_odds":"+150","s_a_odds":"-182","t_line":5.5,"t_o_odds":"+108","t_u_odds":"-132","league_name":"NHL","s_h_line":"-1.5","m_h_improb":0.6108949416,"m_a_improb":0.4291845494,"s_h_improb":0.4,"s_a_improb":0.6453900709,"t_o_improb":0.4807692308,"t_u_improb":0.5689655172,"m_h_dodds":1.6369426752,"m_a_dodds":2.33,"s_h_dodds":2.5,"s_a_dodds":1.5494505495,"t_o_dodds":2.08,"t_u_dodds":1.7575757576,"s_a_pred":1.8039053295,"t_pred":10.1340925271,"m_h_prob":0.571577007,"m_a_prob":0.428422993,"s_h_prob":0.5121222025,"s_a_prob":0.4878777975,"t_o_prob":0.6445797108,"t_u_prob":0.3554202892,"m_h_er":-0.0643612051,"m_a_er":-0.0017744263,"s_h_er":0.2803055063,"s_a_er":-0.2440574786,"t_o_er":0.3407257984,"t_u_er":-0.3753219159,"m_tqe_pick":"away","s_tqe_pick":"home","t_tqe_pick":"over","m_tqe_prob":0.428422993,"s_tqe_prob":0.5121222025,"t_tqe_prob":0.6445797108,"m_tqe_er":-0.0017744263,"s_tqe_er":0.2803055063,"t_tqe_er":0.3407257984},"2":{"GMT_schedule":"2021-05-07T23:00:00.0000000Z","EST_schedule":"2021-05-07 18:00:00","name":"Philadelphia Flyers @ Washington Capitals","h_team":"WSH Capitals","a_team":"PHI Flyers","m_h_odds":"-186","m_a_odds":"+160","s_a_line":"+1.5","s_h_odds":"+120","s_a_odds":"-143","t_line":6.5,"t_o_odds":"+102","t_u_odds":"-125","league_name":"NHL","s_h_line":"-1.5","m_h_improb":0.6503496503,"m_a_improb":0.3846153846,"s_h_improb":0.4545454545,"s_a_improb":0.5884773663,"t_o_improb":0.495049505,"t_u_improb":0.5555555556,"m_h_dodds":1.5376344086,"m_a_dodds":2.6,"s_h_dodds":2.2,"s_a_dodds":1.6993006993,"t_o_dodds":2.02,"t_u_dodds":1.8,"s_a_pred":5.7417268044,"t_pred":11.4741339568,"m_h_prob":0.7170745228,"m_a_prob":0.2829254772,"s_h_prob":0.6642800584,"s_a_prob":0.3357199416,"t_o_prob":0.6546593714,"t_u_prob":0.3453406286,"m_h_er":0.1025984597,"m_a_er":-0.2643937592,"s_h_er":0.4614161285,"s_a_er":-0.4295108685,"t_o_er":0.3224119302,"t_u_er":-0.3783868685,"m_tqe_pick":"home","s_tqe_pick":"home","t_tqe_pick":"over","m_tqe_prob":0.7170745228,"s_tqe_prob":0.6642800584,"t_tqe_prob":0.6546593714,"m_tqe_er":0.1025984597,"s_tqe_er":0.4614161285,"t_tqe_er":0.3224119302},"3":{"GMT_schedule":"2021-05-08T00:00:00.0000000Z","EST_schedule":"2021-05-07 19:00:00","name":"Anaheim Ducks @ Minnesota Wild","h_team":"MIN Wild","a_team":"ANA Ducks","m_h_odds":"-295","m_a_odds":"+245","s_a_line":"+1.5","s_h_odds":"-112","s_a_odds":"-107","t_line":5.5,"t_o_odds":"-110","t_u_odds":"-110","league_name":"NHL","s_h_line":"-1.5","m_h_improb":0.746835443,"m_a_improb":0.2898550725,"s_h_improb":0.5283018868,"s_a_improb":0.5169082126,"t_o_improb":0.5238095238,"t_u_improb":0.5238095238,"m_h_dodds":1.3389830508,"m_a_dodds":3.45,"s_h_dodds":1.8928571429,"s_a_dodds":1.9345794393,"t_o_dodds":1.9090909091,"t_u_dodds":1.9090909091,"s_a_pred":-0.1739087228,"t_pred":5.7212133904,"m_h_prob":0.4930623955,"m_a_prob":0.5069376045,"s_h_prob":0.4335312534,"s_a_prob":0.5664687466,"t_o_prob":0.5070597415,"t_u_prob":0.4929402585,"m_h_er":-0.3397978095,"m_a_er":0.7489347357,"s_h_er":-0.1793872704,"s_a_er":0.0958787902,"t_o_er":-0.0319768572,"t_u_er":-0.0589322337,"m_tqe_pick":"away","s_tqe_pick":"away","t_tqe_pick":"over","m_tqe_prob":0.5069376045,"s_tqe_prob":0.5664687466,"t_tqe_prob":0.5070597415,"m_tqe_er":0.7489347357,"s_tqe_er":0.0958787902,"t_tqe_er":-0.0319768572},"4":{"GMT_schedule":"2021-05-08T02:00:00.0000000Z","EST_schedule":"2021-05-07 21:00:00","name":"Colorado Avalanche @ Los Angeles Kings","h_team":"LA Kings","a_team":"COL Avalanche","m_h_odds":"+235","m_a_odds":"-286","s_a_line":"-1.5","s_h_odds":"-105","s_a_odds":"-113","t_line":5.5,"t_o_odds":"-125","t_u_odds":"+104","league_name":"NHL","s_h_line":"+1.5","m_h_improb":0.2985074627,"m_a_improb":0.7409326425,"s_h_improb":0.512195122,"s_a_improb":0.5305164319,"t_o_improb":0.5555555556,"t_u_improb":0.4901960784,"m_h_dodds":3.35,"m_a_dodds":1.3496503497,"s_h_dodds":1.9523809524,"s_a_dodds":1.8849557522,"t_o_dodds":1.8,"t_u_dodds":2.04,"s_a_pred":-0.2640904705,"t_pred":8.5802022959,"m_h_prob":0.4894655391,"m_a_prob":0.5105344609,"s_h_prob":0.549180422,"s_a_prob":0.450819578,"t_o_prob":0.5973199602,"t_u_prob":0.4026800398,"m_h_er":0.6397095559,"m_a_er":-0.3109569863,"s_h_er":0.0722093953,"s_a_er":-0.1502250432,"t_o_er":0.0751759283,"t_u_er":-0.1785327188,"m_tqe_pick":"home","s_tqe_pick":"home","t_tqe_pick":"over","m_tqe_prob":0.4894655391,"s_tqe_prob":0.549180422,"t_tqe_prob":0.5973199602,"m_tqe_er":0.6397095559,"s_tqe_er":0.0722093953,"t_tqe_er":0.0751759283},"5":{"GMT_schedule":"2021-05-08T02:00:00.0000000Z","EST_schedule":"2021-05-07 21:00:00","name":"St Louis Blues @ Vegas Golden Knights","h_team":"VGS Golden Knights","a_team":"STL Blues","m_h_odds":"-167","m_a_odds":"+143","s_a_line":"+1.5","s_h_odds":"+150","s_a_odds":"-180","t_line":5.5,"t_o_odds":"-110","t_u_odds":"-110","league_name":"NHL","s_h_line":"-1.5","m_h_improb":0.6254681648,"m_a_improb":0.4115226337,"s_h_improb":0.4,"s_a_improb":0.6428571429,"t_o_improb":0.5238095238,"t_u_improb":0.5238095238,"m_h_dodds":1.5988023952,"m_a_dodds":2.43,"s_h_dodds":2.5,"s_a_dodds":1.5555555556,"t_o_dodds":1.9090909091,"t_u_dodds":1.9090909091,"s_a_pred":4.7557631787,"t_pred":5.7212133904,"m_h_prob":0.6828118748,"m_a_prob":0.3171881252,"s_h_prob":0.6276275338,"s_a_prob":0.3723724662,"t_o_prob":0.5070597415,"t_u_prob":0.4929402585,"m_h_er":0.0916812609,"m_a_er":-0.2292328557,"s_h_er":0.5690688346,"s_a_er":-0.4207539415,"t_o_er":-0.0319768572,"t_u_er":-0.0589322337,"m_tqe_pick":"home","s_tqe_pick":"home","t_tqe_pick":"over","m_tqe_prob":0.6828118748,"s_tqe_prob":0.6276275338,"t_tqe_prob":0.5070597415,"m_tqe_er":0.0916812609,"s_tqe_er":0.5690688346,"t_tqe_er":-0.0319768572},"6":{"GMT_schedule":"2021-05-08T02:30:00.0000000Z","EST_schedule":"2021-05-07 21:30:00","name":"Arizona Coyotes @ San Jos\u00e9 Sharks","h_team":"SJ Sharks","a_team":"ARI Coyotes","m_h_odds":"-108","m_a_odds":"-108","s_a_line":"-1.5","s_h_odds":"-275","s_a_odds":"+220","t_line":5.5,"t_o_odds":"-115","t_u_odds":"-106","league_name":"NHL","s_h_line":"+1.5","m_h_improb":0.5192307692,"m_a_improb":0.5192307692,"s_h_improb":0.7333333333,"s_a_improb":0.3125,"t_o_improb":0.5348837209,"t_u_improb":0.5145631068,"m_h_dodds":1.9259259259,"m_a_dodds":1.9259259259,"s_h_dodds":1.3636363636,"s_a_dodds":3.2,"t_o_dodds":1.8695652174,"t_u_dodds":1.9433962264,"s_a_pred":-0.3080064376,"t_pred":0.7728233299,"m_h_prob":0.4877142635,"m_a_prob":0.5122857365,"s_h_prob":0.5474412917,"s_a_prob":0.4525587083,"t_o_prob":0.3526506197,"t_u_prob":0.6473493803,"m_h_er":-0.0606984555,"m_a_er":-0.0133756186,"s_h_er":-0.2534891477,"s_a_er":0.4481878667,"t_o_er":-0.3406966674,"t_u_er":0.2580563428,"m_tqe_pick":"away","s_tqe_pick":"away","t_tqe_pick":"under","m_tqe_prob":0.5122857365,"s_tqe_prob":0.4525587083,"t_tqe_prob":0.6473493803,"m_tqe_er":-0.0133756186,"s_tqe_er":0.4481878667,"t_tqe_er":0.2580563428}}