{"75":{"GMT_schedule":"2021-01-23T12:59:56.0000000Z","EST_schedule":"2021-01-23 07:59:56","h_team":"Huesca","a_team":"Villarreal","m_h_odds":"+1700","m_a_odds":"+650","m_t_odds":"-670","league_name":"La-Liga","m_h_improb":0.0555555556,"m_t_improb":0.8701298701,"m_a_improb":0.1333333333,"m_h_dodds":18.0,"m_t_dodds":1.1492537313,"m_a_dodds":7.5,"m_h_prob":0.0293677333,"m_t_prob":0.8755843459,"m_a_prob":0.0950479208,"m_h_er":-0.4713808,"m_t_er":0.0062685766,"m_a_er":-0.287140594,"m_tqe_pick":"tie"},"94":{"GMT_schedule":"2021-01-23T13:02:11.0000000Z","EST_schedule":"2021-01-23 08:02:11","h_team":"Gen\u00e7lerbirli\u011fi SK","a_team":"Trabzonspor A.\u015e.","m_h_odds":"+11000","m_a_odds":"-1667","m_t_odds":"+850","league_name":"Super-Lig","m_h_improb":0.009009009,"m_t_improb":0.1052631579,"m_a_improb":0.9434069044,"m_h_dodds":111.0,"m_t_dodds":9.5,"m_a_dodds":1.0599880024,"m_h_prob":0.0042813207,"m_t_prob":0.0999126084,"m_a_prob":0.8958060709,"m_h_er":-0.5247733978,"m_t_er":-0.0508302205,"m_a_er":-0.0504563124,"m_tqe_pick":"away"},"56":{"GMT_schedule":"2021-01-23T14:01:32.0000000Z","EST_schedule":"2021-01-23 09:01:32","h_team":"Roma","a_team":"Spezia","m_h_odds":"-143","m_a_odds":"+540","m_t_odds":"+215","league_name":"Serie-A","m_h_improb":0.5884773663,"m_t_improb":0.3174603175,"m_a_improb":0.15625,"m_h_dodds":1.6993006993,"m_t_dodds":3.15,"m_a_dodds":6.4,"m_h_prob":0.5836048496,"m_t_prob":0.304785272,"m_a_prob":0.1116098784,"m_h_er":-0.008279871,"m_t_er":-0.0399263932,"m_a_er":-0.2856967782,"m_tqe_pick":"home"},"21":{"GMT_schedule":"2021-01-23T14:30:01.0000000Z","EST_schedule":"2021-01-23 09:30:01","h_team":"Mainz 05","a_team":"RB Leipzig","m_h_odds":"+2200","m_a_odds":"-835","m_t_odds":"+750","league_name":"Bundesliga","m_h_improb":0.0434782609,"m_t_improb":0.1176470588,"m_a_improb":0.8930481283,"m_h_dodds":23.0,"m_t_dodds":8.5,"m_a_dodds":1.119760479,"m_h_prob":0.0221051145,"m_t_prob":0.1160071492,"m_a_prob":0.8618877363,"m_h_er":-0.4915823669,"m_t_er":-0.0139392316,"m_a_er":-0.0348921755,"m_tqe_pick":"tie"},"23":{"GMT_schedule":"2021-01-23T14:30:02.0000000Z","EST_schedule":"2021-01-23 09:30:02","h_team":"Bayer Leverkusen","a_team":"VfL Wolfsburg","m_h_odds":"-124","m_a_odds":"+300","m_t_odds":"+275","league_name":"Bundesliga","m_h_improb":0.5535714286,"m_t_improb":0.2666666667,"m_a_improb":0.25,"m_h_dodds":1.8064516129,"m_t_dodds":3.75,"m_a_dodds":4.0,"m_h_prob":0.5438924204,"m_t_prob":0.246847636,"m_a_prob":0.2092599436,"m_h_er":-0.0174846599,"m_t_er":-0.0743213651,"m_a_er":-0.1629602255,"m_tqe_pick":"home"},"22":{"GMT_schedule":"2021-01-23T14:30:02.0000000Z","EST_schedule":"2021-01-23 09:30:02","h_team":"SC Freiburg","a_team":"VfB Stuttgart","m_h_odds":"+225","m_a_odds":"+116","m_t_odds":"+245","league_name":"Bundesliga","m_h_improb":0.3076923077,"m_t_improb":0.2898550725,"m_a_improb":0.462962963,"m_h_dodds":3.25,"m_t_dodds":3.45,"m_a_dodds":2.16,"m_h_prob":0.2775037533,"m_t_prob":0.2641909762,"m_a_prob":0.4583052705,"m_h_er":-0.0981128017,"m_t_er":-0.088541132,"m_a_er":-0.0100606158,"m_tqe_pick":"away"},"24":{"GMT_schedule":"2021-01-23T14:30:05.0000000Z","EST_schedule":"2021-01-23 09:30:05","h_team":"FC Augsburg","a_team":"1. FC Union Berlin","m_h_odds":"-112","m_a_odds":"+330","m_t_odds":"+235","league_name":"Bundesliga","m_h_improb":0.5283018868,"m_t_improb":0.2985074627,"m_a_improb":0.2325581395,"m_h_dodds":1.8928571429,"m_t_dodds":3.35,"m_a_dodds":4.3,"m_h_prob":0.5319176171,"m_t_prob":0.2783782693,"m_a_prob":0.1897041136,"m_h_er":0.006844061,"m_t_er":-0.0674327979,"m_a_er":-0.1842723115,"m_tqe_pick":"home"},"25":{"GMT_schedule":"2021-01-23T14:30:35.0000000Z","EST_schedule":"2021-01-23 09:30:35","h_team":"Arminia Bielefeld","a_team":"Eintracht Frankfurt","m_h_odds":"+410","m_a_odds":"-148","m_t_odds":"+270","league_name":"Bundesliga","m_h_improb":0.1960784314,"m_t_improb":0.2702702703,"m_a_improb":0.5967741935,"m_h_dodds":5.1,"m_t_dodds":3.7,"m_a_dodds":1.6756756757,"m_h_prob":0.145569495,"m_t_prob":0.2625801552,"m_a_prob":0.5918503498,"m_h_er":-0.2575955756,"m_t_er":-0.0284534258,"m_a_er":-0.0082507651,"m_tqe_pick":"away"},"76":{"GMT_schedule":"2021-01-23T15:15:00.0000000Z","EST_schedule":"2021-01-23 10:15:00","h_team":"Sevilla","a_team":"Cadiz","m_h_odds":"-215","m_a_odds":"+750","m_t_odds":"+300","league_name":"La-Liga","m_h_improb":0.6825396825,"m_t_improb":0.25,"m_a_improb":0.1176470588,"m_h_dodds":1.4651162791,"m_t_dodds":4.0,"m_a_dodds":8.5,"m_h_prob":0.6650815991,"m_t_prob":0.253176112,"m_a_prob":0.0817422889,"m_h_er":-0.0255781223,"m_t_er":0.012704448,"m_a_er":-0.3051905442,"m_tqe_pick":"tie"},"38":{"GMT_schedule":"2021-01-23T16:00:00.0000000Z","EST_schedule":"2021-01-23 11:00:00","h_team":"Lens","a_team":"Nice","m_h_odds":"-103","m_a_odds":"+285","m_t_odds":"+235","league_name":"Ligue-1","m_h_improb":0.5073891626,"m_t_improb":0.2985074627,"m_a_improb":0.2597402597,"m_h_dodds":1.9708737864,"m_t_dodds":3.35,"m_a_dodds":3.85,"m_h_prob":0.5076114463,"m_t_prob":0.2734345548,"m_a_prob":0.2189539989,"m_h_er":0.0004380932,"m_t_er":-0.0839942414,"m_a_er":-0.1570271044,"m_tqe_pick":"home"},"95":{"GMT_schedule":"2021-01-23T16:00:00.0000000Z","EST_schedule":"2021-01-23 11:00:00","h_team":"\u0130stanbul Ba\u015fak\u015fehir","a_team":"\u00c7aykur Rizespor","m_h_odds":"-335","m_a_odds":"+750","m_t_odds":"+410","league_name":"Super-Lig","m_h_improb":0.7701149425,"m_t_improb":0.1960784314,"m_a_improb":0.1176470588,"m_h_dodds":1.2985074627,"m_t_dodds":5.1,"m_a_dodds":8.5,"m_h_prob":0.7225090745,"m_t_prob":0.1965712342,"m_a_prob":0.0809196913,"m_h_er":-0.0618165749,"m_t_er":0.0025132944,"m_a_er":-0.3121826237,"m_tqe_pick":"tie"},"57":{"GMT_schedule":"2021-01-23T17:00:00.0000000Z","EST_schedule":"2021-01-23 12:00:00","h_team":"Udinese","a_team":"Inter","m_h_odds":"+500","m_a_odds":"-175","m_t_odds":"+290","league_name":"Serie-A","m_h_improb":0.1666666667,"m_t_improb":0.2564102564,"m_a_improb":0.6363636364,"m_h_dodds":6.0,"m_t_dodds":3.9,"m_a_dodds":1.5714285714,"m_h_prob":0.1161464748,"m_t_prob":0.2547655943,"m_a_prob":0.6290879309,"m_h_er":-0.3031211512,"m_t_er":-0.0064141822,"m_a_er":-0.0114332515,"m_tqe_pick":"tie"},"58":{"GMT_schedule":"2021-01-23T17:00:00.0000000Z","EST_schedule":"2021-01-23 12:00:00","h_team":"AC Milan","a_team":"Atalanta","m_h_odds":"+200","m_a_odds":"+128","m_t_odds":"+260","league_name":"Serie-A","m_h_improb":0.3333333333,"m_t_improb":0.2777777778,"m_a_improb":0.4385964912,"m_h_dodds":3.0,"m_t_dodds":3.6,"m_a_dodds":2.28,"m_h_prob":0.3125096099,"m_t_prob":0.2531872676,"m_a_prob":0.4343031225,"m_h_er":-0.0624711704,"m_t_er":-0.0885258366,"m_a_er":-0.0097888807,"m_tqe_pick":"away"},"26":{"GMT_schedule":"2021-01-23T17:30:00.0000000Z","EST_schedule":"2021-01-23 12:30:00","h_team":"Hertha BSC","a_team":"Werder Bremen","m_h_odds":"+120","m_a_odds":"+230","m_t_odds":"+235","league_name":"Bundesliga","m_h_improb":0.4545454545,"m_t_improb":0.2985074627,"m_a_improb":0.303030303,"m_h_dodds":2.2,"m_t_dodds":3.35,"m_a_dodds":3.3,"m_h_prob":0.457652332,"m_t_prob":0.2711373023,"m_a_prob":0.2712103657,"m_h_er":0.0068351303,"m_t_er":-0.0916900372,"m_a_er":-0.1050057932,"m_tqe_pick":"home"},"77":{"GMT_schedule":"2021-01-23T17:30:00.0000000Z","EST_schedule":"2021-01-23 12:30:00","h_team":"Real Sociedad","a_team":"Real Betis","m_h_odds":"-129","m_a_odds":"+330","m_t_odds":"+285","league_name":"La-Liga","m_h_improb":0.5633187773,"m_t_improb":0.2597402597,"m_a_improb":0.2325581395,"m_h_dodds":1.7751937984,"m_t_dodds":3.85,"m_a_dodds":4.3,"m_h_prob":0.5617069461,"m_t_prob":0.2457939954,"m_a_prob":0.1924990584,"m_h_er":-0.0028613127,"m_t_er":-0.0536931176,"m_a_er":-0.1722540487,"m_tqe_pick":"home"},"59":{"GMT_schedule":"2021-01-23T19:45:00.0000000Z","EST_schedule":"2021-01-23 14:45:00","h_team":"Fiorentina","a_team":"Crotone","m_h_odds":"-152","m_a_odds":"+420","m_t_odds":"+290","league_name":"Serie-A","m_h_improb":0.6031746032,"m_t_improb":0.2564102564,"m_a_improb":0.1923076923,"m_h_dodds":1.6578947368,"m_t_dodds":3.9,"m_a_dodds":5.2,"m_h_prob":0.5995531262,"m_t_prob":0.2497205103,"m_a_prob":0.1507263635,"m_h_er":-0.0060040276,"m_t_er":-0.0260900097,"m_a_er":-0.21622291,"m_tqe_pick":"home"},"39":{"GMT_schedule":"2021-01-23T20:00:00.0000000Z","EST_schedule":"2021-01-23 15:00:00","h_team":"Monaco","a_team":"Marseille","m_h_odds":"-124","m_a_odds":"+310","m_t_odds":"+270","league_name":"Ligue-1","m_h_improb":0.5535714286,"m_t_improb":0.2702702703,"m_a_improb":0.243902439,"m_h_dodds":1.8064516129,"m_t_dodds":3.7,"m_a_dodds":4.1,"m_h_prob":0.5461178968,"m_t_prob":0.2512071049,"m_a_prob":0.2026749982,"m_h_er":-0.0134644445,"m_t_er":-0.0705337117,"m_a_er":-0.1690325072,"m_tqe_pick":"home"},"0":{"GMT_schedule":"2021-01-23T20:00:00.0000000Z","EST_schedule":"2021-01-23 15:00:00","h_team":"Aston Villa","a_team":"Newcastle","m_h_odds":"-205","m_a_odds":"+540","m_t_odds":"+360","league_name":"EPL","m_h_improb":0.6721311475,"m_t_improb":0.2173913043,"m_a_improb":0.15625,"m_h_dodds":1.487804878,"m_t_dodds":4.6,"m_a_dodds":6.4,"m_h_prob":0.6611256619,"m_t_prob":0.2208000912,"m_a_prob":0.1180742469,"m_h_er":-0.0163740152,"m_t_er":0.0156804195,"m_a_er":-0.2443248197,"m_tqe_pick":"tie"},"78":{"GMT_schedule":"2021-01-23T20:00:00.0000000Z","EST_schedule":"2021-01-23 15:00:00","h_team":"Alav\u00e9s","a_team":"Real Madrid","m_h_odds":"+550","m_a_odds":"-200","m_t_odds":"+330","league_name":"La-Liga","m_h_improb":0.1538461538,"m_t_improb":0.2325581395,"m_a_improb":0.6666666667,"m_h_dodds":6.5,"m_t_dodds":4.3,"m_a_dodds":1.5,"m_h_prob":0.1051199538,"m_t_prob":0.2353515156,"m_a_prob":0.6595285306,"m_h_er":-0.3167203002,"m_t_er":0.0120115171,"m_a_er":-0.0107072041,"m_tqe_pick":"tie"},"96":{"GMT_schedule":"2021-01-24T10:30:00.0000000Z","EST_schedule":"2021-01-24 05:30:00","h_team":"Konyaspor","a_team":"Antalyaspor A.\u015e.","m_h_odds":"+118","m_a_odds":"+220","m_t_odds":"+230","league_name":"Super-Lig","m_h_improb":0.4587155963,"m_t_improb":0.303030303,"m_a_improb":0.3125,"m_h_dodds":2.18,"m_t_dodds":3.3,"m_a_dodds":3.2,"m_h_prob":0.4525714529,"m_t_prob":0.2697941816,"m_a_prob":0.2776343655,"m_h_er":-0.0133942327,"m_t_er":-0.1096792007,"m_a_er":-0.1115700304,"m_tqe_pick":"home"},"60":{"GMT_schedule":"2021-01-24T11:30:00.0000000Z","EST_schedule":"2021-01-24 06:30:00","h_team":"Juventus","a_team":"Bologna","m_h_odds":"-250","m_a_odds":"+650","m_t_odds":"+390","league_name":"Serie-A","m_h_improb":0.7142857143,"m_t_improb":0.2040816327,"m_a_improb":0.1333333333,"m_h_dodds":1.4,"m_t_dodds":4.9,"m_a_dodds":7.5,"m_h_prob":0.6937894475,"m_t_prob":0.2093270024,"m_a_prob":0.0968835501,"m_h_er":-0.0286947735,"m_t_er":0.0257023117,"m_a_er":-0.273373374,"m_tqe_pick":"tie"},"40":{"GMT_schedule":"2021-01-24T12:00:00.0000000Z","EST_schedule":"2021-01-24 07:00:00","h_team":"Bordeaux","a_team":"Angers","m_h_odds":"+138","m_a_odds":"+210","m_t_odds":"+210","league_name":"Ligue-1","m_h_improb":0.4201680672,"m_t_improb":0.3225806452,"m_a_improb":0.3225806452,"m_h_dodds":2.38,"m_t_dodds":3.1,"m_a_dodds":3.1,"m_h_prob":0.4169578494,"m_t_prob":0.2900086552,"m_a_prob":0.2930334955,"m_h_er":-0.0076403185,"m_t_er":-0.1009731689,"m_a_er":-0.0915961641,"m_tqe_pick":"home"},"98":{"GMT_schedule":"2021-01-24T13:00:00.0000000Z","EST_schedule":"2021-01-24 08:00:00","h_team":"Yeni Malatyaspor","a_team":"Galatasaray A.\u015e.","m_h_odds":"+290","m_a_odds":"-118","m_t_odds":"+260","league_name":"Super-Lig","m_h_improb":0.2564102564,"m_t_improb":0.2777777778,"m_a_improb":0.5412844037,"m_h_dodds":3.9,"m_t_dodds":3.6,"m_a_dodds":1.8474576271,"m_h_prob":0.2123868962,"m_t_prob":0.257497707,"m_a_prob":0.5301153968,"m_h_er":-0.1716911048,"m_t_er":-0.0730082547,"m_a_er":-0.020634267,"m_tqe_pick":"away"},"79":{"GMT_schedule":"2021-01-24T13:00:00.0000000Z","EST_schedule":"2021-01-24 08:00:00","h_team":"Osasuna","a_team":"Granada CF","m_h_odds":"+150","m_a_odds":"+220","m_t_odds":"+195","league_name":"La-Liga","m_h_improb":0.4,"m_t_improb":0.3389830508,"m_a_improb":0.3125,"m_h_dodds":2.5,"m_t_dodds":2.95,"m_a_dodds":3.2,"m_h_prob":0.4021827989,"m_t_prob":0.3113765607,"m_a_prob":0.2864406404,"m_h_er":0.0054569973,"m_t_er":-0.081439146,"m_a_er":-0.0833899508,"m_tqe_pick":"home"},"97":{"GMT_schedule":"2021-01-24T13:00:00.0000000Z","EST_schedule":"2021-01-24 08:00:00","h_team":"Denizlispor","a_team":"Fatih Karag\u00fcmr\u00fck","m_h_odds":"+180","m_a_odds":"+133","m_t_odds":"+245","league_name":"Super-Lig","m_h_improb":0.3571428571,"m_t_improb":0.2898550725,"m_a_improb":0.4291845494,"m_h_dodds":2.8,"m_t_dodds":3.45,"m_a_dodds":2.33,"m_h_prob":0.3334520094,"m_t_prob":0.2557093695,"m_a_prob":0.4108386211,"m_h_er":-0.0663343736,"m_t_er":-0.1178026753,"m_a_er":-0.0427460129,"m_tqe_pick":"away"},"43":{"GMT_schedule":"2021-01-24T14:00:00.0000000Z","EST_schedule":"2021-01-24 09:00:00","h_team":"Dijon","a_team":"Strasbourg","m_h_odds":"+260","m_a_odds":"-103","m_t_odds":"+250","league_name":"Ligue-1","m_h_improb":0.2777777778,"m_t_improb":0.2857142857,"m_a_improb":0.5073891626,"m_h_dodds":3.6,"m_t_dodds":3.5,"m_a_dodds":1.9708737864,"m_h_prob":0.2384087815,"m_t_prob":0.262002104,"m_a_prob":0.4995891145,"m_h_er":-0.1417283867,"m_t_er":-0.0829926359,"m_a_er":-0.0153729103,"m_tqe_pick":"away"},"42":{"GMT_schedule":"2021-01-24T14:00:00.0000000Z","EST_schedule":"2021-01-24 09:00:00","h_team":"Reims","a_team":"Brest","m_h_odds":"+135","m_a_odds":"+190","m_t_odds":"+240","league_name":"Ligue-1","m_h_improb":0.4255319149,"m_t_improb":0.2941176471,"m_a_improb":0.3448275862,"m_h_dodds":2.35,"m_t_dodds":3.4,"m_a_dodds":2.9,"m_h_prob":0.4194674228,"m_t_prob":0.2622723884,"m_a_prob":0.3182601888,"m_h_er":-0.0142515565,"m_t_er":-0.1082738793,"m_a_er":-0.0770454525,"m_tqe_pick":"home"},"41":{"GMT_schedule":"2021-01-24T14:00:00.0000000Z","EST_schedule":"2021-01-24 09:00:00","h_team":"Metz","a_team":"Nantes","m_h_odds":"+145","m_a_odds":"+205","m_t_odds":"+205","league_name":"Ligue-1","m_h_improb":0.4081632653,"m_t_improb":0.3278688525,"m_a_improb":0.3278688525,"m_h_dodds":2.45,"m_t_dodds":3.05,"m_a_dodds":3.05,"m_h_prob":0.4041844313,"m_t_prob":0.2954447572,"m_a_prob":0.3003708115,"m_h_er":-0.0097481434,"m_t_er":-0.0988934904,"m_a_er":-0.0838690249,"m_tqe_pick":"home"},"61":{"GMT_schedule":"2021-01-24T14:00:00.0000000Z","EST_schedule":"2021-01-24 09:00:00","h_team":"Genoa","a_team":"Cagliari","m_h_odds":"+123","m_a_odds":"+215","m_t_odds":"+250","league_name":"Serie-A","m_h_improb":0.4484304933,"m_t_improb":0.2857142857,"m_a_improb":0.3174603175,"m_h_dodds":2.23,"m_t_dodds":3.5,"m_a_dodds":3.15,"m_h_prob":0.4512725747,"m_t_prob":0.2593558596,"m_a_prob":0.2893715657,"m_h_er":0.0063378417,"m_t_er":-0.0922544915,"m_a_er":-0.088479568,"m_tqe_pick":"home"},"62":{"GMT_schedule":"2021-01-24T14:00:00.0000000Z","EST_schedule":"2021-01-24 09:00:00","h_team":"Hellas Verona","a_team":"Napoli","m_h_odds":"+410","m_a_odds":"-148","m_t_odds":"+280","league_name":"Serie-A","m_h_improb":0.1960784314,"m_t_improb":0.2631578947,"m_a_improb":0.5967741935,"m_h_dodds":5.1,"m_t_dodds":3.8,"m_a_dodds":1.6756756757,"m_h_prob":0.1465823798,"m_t_prob":0.2574491256,"m_a_prob":0.5959684946,"m_h_er":-0.2524298629,"m_t_er":-0.0216933227,"m_a_er":-0.0013500902,"m_tqe_pick":"away"},"27":{"GMT_schedule":"2021-01-24T14:30:00.0000000Z","EST_schedule":"2021-01-24 09:30:00","h_team":"FC Schalke 04","a_team":"Bayern Munich","m_h_odds":"+1200","m_a_odds":"-590","m_t_odds":"+700","league_name":"Bundesliga","m_h_improb":0.0769230769,"m_t_improb":0.125,"m_a_improb":0.8550724638,"m_h_dodds":13.0,"m_t_dodds":8.0,"m_a_dodds":1.1694915254,"m_h_prob":0.0425035621,"m_t_prob":0.1260666566,"m_a_prob":0.8314297813,"m_h_er":-0.4474536925,"m_t_er":0.008533253,"m_a_er":-0.0276499168,"m_tqe_pick":"tie"},"80":{"GMT_schedule":"2021-01-24T15:15:00.0000000Z","EST_schedule":"2021-01-24 10:15:00","h_team":"Elche","a_team":"FC Barcelona","m_h_odds":"+700","m_a_odds":"-275","m_t_odds":"+410","league_name":"La-Liga","m_h_improb":0.125,"m_t_improb":0.1960784314,"m_a_improb":0.7333333333,"m_h_dodds":8.0,"m_t_dodds":5.1,"m_a_dodds":1.3636363636,"m_h_prob":0.0797631878,"m_t_prob":0.2016722843,"m_a_prob":0.7185645279,"m_h_er":-0.3618944978,"m_t_er":0.0285286499,"m_a_er":-0.0201392801,"m_tqe_pick":"tie"},"99":{"GMT_schedule":"2021-01-24T16:00:00.0000000Z","EST_schedule":"2021-01-24 11:00:00","h_team":"Be\u015fikta\u015f A.\u015e.","a_team":"G\u00f6ztepe A.\u015e.","m_h_odds":"-278","m_a_odds":"+650","m_t_odds":"+380","league_name":"Super-Lig","m_h_improb":0.7354497354,"m_t_improb":0.2083333333,"m_a_improb":0.1333333333,"m_h_dodds":1.3597122302,"m_t_dodds":4.8,"m_a_dodds":7.5,"m_h_prob":0.6954895742,"m_t_prob":0.2095176525,"m_a_prob":0.0949927733,"m_h_er":-0.05433432,"m_t_er":0.0056847322,"m_a_er":-0.2875542002,"m_tqe_pick":"tie"},"44":{"GMT_schedule":"2021-01-24T16:00:00.0000000Z","EST_schedule":"2021-01-24 11:00:00","h_team":"Rennes","a_team":"Lille","m_h_odds":"+170","m_a_odds":"+170","m_t_odds":"+205","league_name":"Ligue-1","m_h_improb":0.3703703704,"m_t_improb":0.3278688525,"m_a_improb":0.3703703704,"m_h_dodds":2.7,"m_t_dodds":3.05,"m_a_dodds":2.7,"m_h_prob":0.3555679307,"m_t_prob":0.293637419,"m_a_prob":0.3507946503,"m_h_er":-0.0399665872,"m_t_er":-0.1044058721,"m_a_er":-0.0528544441,"m_tqe_pick":"home"},"100":{"GMT_schedule":"2021-01-24T16:00:00.0000000Z","EST_schedule":"2021-01-24 11:00:00","h_team":"Gaziantep B.B.","a_team":"Hatayspor","m_h_odds":"+133","m_a_odds":"+215","m_t_odds":"+205","league_name":"Super-Lig","m_h_improb":0.4291845494,"m_t_improb":0.3278688525,"m_a_improb":0.3174603175,"m_h_dodds":2.33,"m_t_dodds":3.05,"m_a_dodds":3.15,"m_h_prob":0.4233950397,"m_t_prob":0.2923544366,"m_a_prob":0.2842505237,"m_h_er":-0.0134895575,"m_t_er":-0.1083189685,"m_a_er":-0.1046108502,"m_tqe_pick":"home"},"28":{"GMT_schedule":"2021-01-24T17:00:00.0000000Z","EST_schedule":"2021-01-24 12:00:00","h_team":"TSG Hoffenheim","a_team":"1. FC K\u00f6ln","m_h_odds":"-132","m_a_odds":"+380","m_t_odds":"+260","league_name":"Bundesliga","m_h_improb":0.5689655172,"m_t_improb":0.2777777778,"m_a_improb":0.2083333333,"m_h_dodds":1.7575757576,"m_t_dodds":3.6,"m_a_dodds":4.8,"m_h_prob":0.5694913721,"m_t_prob":0.2650093504,"m_a_prob":0.1654992776,"m_h_er":0.0009242297,"m_t_er":-0.0459663386,"m_a_er":-0.2056034677,"m_tqe_pick":"home"},"63":{"GMT_schedule":"2021-01-24T17:00:00.0000000Z","EST_schedule":"2021-01-24 12:00:00","h_team":"Lazio","a_team":"Sassuolo","m_h_odds":"-141","m_a_odds":"+370","m_t_odds":"+290","league_name":"Serie-A","m_h_improb":0.5850622407,"m_t_improb":0.2564102564,"m_a_improb":0.2127659574,"m_h_dodds":1.7092198582,"m_t_dodds":3.9,"m_a_dodds":4.7,"m_h_prob":0.5820187379,"m_t_prob":0.2462543053,"m_a_prob":0.1717269568,"m_h_er":-0.0052020154,"m_t_er":-0.0396082092,"m_a_er":-0.192883303,"m_tqe_pick":"home"},"81":{"GMT_schedule":"2021-01-24T17:30:00.0000000Z","EST_schedule":"2021-01-24 12:30:00","h_team":"Celta Vigo","a_team":"Eibar","m_h_odds":"+106","m_a_odds":"+265","m_t_odds":"+240","league_name":"La-Liga","m_h_improb":0.4854368932,"m_t_improb":0.2941176471,"m_a_improb":0.2739726027,"m_h_dodds":2.06,"m_t_dodds":3.4,"m_a_dodds":3.65,"m_h_prob":0.4919480706,"m_t_prob":0.2704832149,"m_a_prob":0.2375687145,"m_h_er":0.0134130255,"m_t_er":-0.0803570693,"m_a_er":-0.1328741922,"m_tqe_pick":"home"},"64":{"GMT_schedule":"2021-01-24T19:45:00.0000000Z","EST_schedule":"2021-01-24 14:45:00","h_team":"Parma","a_team":"Sampdoria","m_h_odds":"+200","m_a_odds":"+138","m_t_odds":"+235","league_name":"Serie-A","m_h_improb":0.3333333333,"m_t_improb":0.2985074627,"m_a_improb":0.4201680672,"m_h_dodds":3.0,"m_t_dodds":3.35,"m_a_dodds":2.38,"m_h_prob":0.3127064475,"m_t_prob":0.2722532136,"m_a_prob":0.4150403389,"m_h_er":-0.0618806574,"m_t_er":-0.0879517344,"m_a_er":-0.0122039935,"m_tqe_pick":"away"},"45":{"GMT_schedule":"2021-01-24T20:00:00.0000000Z","EST_schedule":"2021-01-24 15:00:00","h_team":"Saint-\u00c9tienne","a_team":"Lyon","m_h_odds":"+650","m_a_odds":"-250","m_t_odds":"+370","league_name":"Ligue-1","m_h_improb":0.1333333333,"m_t_improb":0.2127659574,"m_a_improb":0.7142857143,"m_h_dodds":7.5,"m_t_dodds":4.7,"m_a_dodds":1.4,"m_h_prob":0.0863351078,"m_t_prob":0.21678008,"m_a_prob":0.6968848123,"m_h_er":-0.3524866918,"m_t_er":0.0188663758,"m_a_er":-0.0243612628,"m_tqe_pick":"tie"},"82":{"GMT_schedule":"2021-01-24T20:00:00.0000000Z","EST_schedule":"2021-01-24 15:00:00","h_team":"Atl\u00e9tico Madrid","a_team":"Valencia","m_h_odds":"-235","m_a_odds":"+700","m_t_odds":"+340","league_name":"La-Liga","m_h_improb":0.7014925373,"m_t_improb":0.2272727273,"m_a_improb":0.125,"m_h_dodds":1.4255319149,"m_t_dodds":4.4,"m_a_dodds":8.0,"m_h_prob":0.6800548603,"m_t_prob":0.2313449499,"m_a_prob":0.0886001898,"m_h_er":-0.0305600928,"m_t_er":0.0179177797,"m_a_er":-0.2911984816,"m_tqe_pick":"tie"},"101":{"GMT_schedule":"2021-01-25T13:00:00.0000000Z","EST_schedule":"2021-01-25 08:00:00","h_team":"Kas\u0131mpa\u015fa","a_team":"Sivasspor","m_h_odds":"+205","m_a_odds":"+133","m_t_odds":"+215","league_name":"Super-Lig","m_h_improb":0.3278688525,"m_t_improb":0.3174603175,"m_a_improb":0.4291845494,"m_h_dodds":3.05,"m_t_dodds":3.15,"m_a_dodds":2.33,"m_h_prob":0.2994128692,"m_t_prob":0.2839888905,"m_a_prob":0.4165982404,"m_h_er":-0.0867907491,"m_t_er":-0.105434995,"m_a_er":-0.0293261,"m_tqe_pick":"away"},"102":{"GMT_schedule":"2021-01-25T16:00:00.0000000Z","EST_schedule":"2021-01-25 11:00:00","h_team":"Fenerbah\u00e7e","a_team":"Kayserispor","m_h_odds":"-315","m_a_odds":"+750","m_t_odds":"+400","league_name":"Super-Lig","m_h_improb":0.7590361446,"m_t_improb":0.2,"m_a_improb":0.1176470588,"m_h_dodds":1.3174603175,"m_t_dodds":5.0,"m_a_dodds":8.5,"m_h_prob":0.7168710061,"m_t_prob":0.2017185772,"m_a_prob":0.0814104167,"m_h_er":-0.0555508968,"m_t_er":0.0085928862,"m_a_er":-0.3080114581,"m_tqe_pick":"tie"},"103":{"GMT_schedule":"2021-01-25T16:00:00.0000000Z","EST_schedule":"2021-01-25 11:00:00","h_team":"Alanyaspor","a_team":"Ankarag\u00fcc\u00fc","m_h_odds":"-225","m_a_odds":"+525","m_t_odds":"+335","league_name":"Super-Lig","m_h_improb":0.6923076923,"m_t_improb":0.2298850575,"m_a_improb":0.16,"m_h_dodds":1.4444444444,"m_t_dodds":4.35,"m_a_dodds":6.25,"m_h_prob":0.6543679564,"m_t_prob":0.2270796293,"m_a_prob":0.1185524142,"m_h_er":-0.0548018407,"m_t_er":-0.0122036124,"m_a_er":-0.259047411,"m_tqe_pick":"tie"},"83":{"GMT_schedule":"2021-01-25T20:00:00.0000000Z","EST_schedule":"2021-01-25 15:00:00","h_team":"Athletic Club Bilbao","a_team":"Getafe","m_h_odds":"+130","m_a_odds":"+250","m_t_odds":"+200","league_name":"La-Liga","m_h_improb":0.4347826087,"m_t_improb":0.3333333333,"m_a_improb":0.2857142857,"m_h_dodds":2.3,"m_t_dodds":3.0,"m_a_dodds":3.5,"m_h_prob":0.4420161379,"m_t_prob":0.3060015681,"m_a_prob":0.251982294,"m_h_er":0.0166371172,"m_t_er":-0.0819952958,"m_a_er":-0.118061971,"m_tqe_pick":"home"},"2":{"GMT_schedule":"2021-01-26T18:00:00.0000000Z","EST_schedule":"2021-01-26 13:00:00","h_team":"Crystal Palace","a_team":"West Ham","m_h_odds":"+220","m_a_odds":"+132","m_t_odds":"+230","league_name":"EPL","m_h_improb":0.3125,"m_t_improb":0.303030303,"m_a_improb":0.4310344828,"m_h_dodds":3.2,"m_t_dodds":3.3,"m_a_dodds":2.32,"m_h_prob":0.2879050757,"m_t_prob":0.2799237939,"m_a_prob":0.4321711304,"m_h_er":-0.0787037577,"m_t_er":-0.07625148,"m_a_er":0.0026370224,"m_tqe_pick":"away"},"1":{"GMT_schedule":"2021-01-26T18:00:00.0000000Z","EST_schedule":"2021-01-26 13:00:00","h_team":"Newcastle","a_team":"Leeds United","m_h_odds":"+270","m_a_odds":"-108","m_t_odds":"+290","league_name":"EPL","m_h_improb":0.2702702703,"m_t_improb":0.2564102564,"m_a_improb":0.5192307692,"m_h_dodds":3.7,"m_t_dodds":3.9,"m_a_dodds":1.9259259259,"m_h_prob":0.2348955345,"m_t_prob":0.2418631893,"m_a_prob":0.5232412762,"m_h_er":-0.1308865224,"m_t_er":-0.0567335617,"m_a_er":0.0077239394,"m_tqe_pick":"away"},"4":{"GMT_schedule":"2021-01-26T20:15:00.0000000Z","EST_schedule":"2021-01-26 15:15:00","h_team":"West Bromwich","a_team":"Manchester City","m_h_odds":"+1300","m_a_odds":"-530","m_t_odds":"+600","league_name":"EPL","m_h_improb":0.0714285714,"m_t_improb":0.1428571429,"m_a_improb":0.8412698413,"m_h_dodds":14.0,"m_t_dodds":7.0,"m_a_dodds":1.1886792453,"m_h_prob":0.0391094082,"m_t_prob":0.1444629615,"m_a_prob":0.8164276303,"m_h_er":-0.4524682854,"m_t_er":0.0112407305,"m_a_er":-0.0295294206,"m_tqe_pick":"tie"},"3":{"GMT_schedule":"2021-01-26T20:15:00.0000000Z","EST_schedule":"2021-01-26 15:15:00","h_team":"Southampton","a_team":"Arsenal","m_h_odds":"+210","m_a_odds":"+132","m_t_odds":"+240","league_name":"EPL","m_h_improb":0.3225806452,"m_t_improb":0.2941176471,"m_a_improb":0.4310344828,"m_h_dodds":3.1,"m_t_dodds":3.4,"m_a_dodds":2.32,"m_h_prob":0.3001484791,"m_t_prob":0.2701427455,"m_a_prob":0.4297087754,"m_h_er":-0.0695397149,"m_t_er":-0.0815146653,"m_a_er":-0.003075641,"m_tqe_pick":"away"},"5":{"GMT_schedule":"2021-01-27T18:00:00.0000000Z","EST_schedule":"2021-01-27 13:00:00","h_team":"Burnley","a_team":"Aston Villa","m_h_odds":"+220","m_a_odds":"+123","m_t_odds":"+250","league_name":"EPL","m_h_improb":0.3125,"m_t_improb":0.2857142857,"m_a_improb":0.4484304933,"m_h_dodds":3.2,"m_t_dodds":3.5,"m_a_dodds":2.23,"m_h_prob":0.2873122879,"m_t_prob":0.2633847285,"m_a_prob":0.4493029837,"m_h_er":-0.0806006789,"m_t_er":-0.0781534503,"m_a_er":0.0019456536,"m_tqe_pick":"away"},"6":{"GMT_schedule":"2021-01-27T18:00:00.0000000Z","EST_schedule":"2021-01-27 13:00:00","h_team":"Chelsea","a_team":"Wolves","m_h_odds":"-165","m_a_odds":"+420","m_t_odds":"+335","league_name":"EPL","m_h_improb":0.6226415094,"m_t_improb":0.2298850575,"m_a_improb":0.1923076923,"m_h_dodds":1.6060606061,"m_t_dodds":4.35,"m_a_dodds":5.2,"m_h_prob":0.6192073401,"m_t_prob":0.2275801902,"m_a_prob":0.1532124697,"m_h_er":-0.005515484,"m_t_er":-0.0100261728,"m_a_er":-0.2032951575,"m_tqe_pick":"home"},"7":{"GMT_schedule":"2021-01-27T19:30:00.0000000Z","EST_schedule":"2021-01-27 14:30:00","h_team":"Brighton","a_team":"Fulham","m_h_odds":"+107","m_a_odds":"+265","m_t_odds":"+245","league_name":"EPL","m_h_improb":0.4830917874,"m_t_improb":0.2898550725,"m_a_improb":0.2739726027,"m_h_dodds":2.07,"m_t_dodds":3.45,"m_a_dodds":3.65,"m_h_prob":0.4928573894,"m_t_prob":0.2681551112,"m_a_prob":0.2389874994,"m_h_er":0.020214796,"m_t_er":-0.0748648664,"m_a_er":-0.127695627,"m_tqe_pick":"home"},"8":{"GMT_schedule":"2021-01-27T20:15:00.0000000Z","EST_schedule":"2021-01-27 15:15:00","h_team":"Manchester United","a_team":"Sheffield United","m_h_odds":"-420","m_a_odds":"+1150","m_t_odds":"+525","league_name":"EPL","m_h_improb":0.8076923077,"m_t_improb":0.16,"m_a_improb":0.08,"m_h_dodds":1.2380952381,"m_t_dodds":6.25,"m_a_dodds":12.5,"m_h_prob":0.782211889,"m_t_prob":0.1649084169,"m_a_prob":0.0528796941,"m_h_er":-0.031547185,"m_t_er":0.0306776055,"m_a_er":-0.3390038235,"m_tqe_pick":"tie"},"9":{"GMT_schedule":"2021-01-27T20:15:00.0000000Z","EST_schedule":"2021-01-27 15:15:00","h_team":"Everton","a_team":"Leicester City","m_h_odds":"+170","m_a_odds":"+165","m_t_odds":"+230","league_name":"EPL","m_h_improb":0.3703703704,"m_t_improb":0.303030303,"m_a_improb":0.3773584906,"m_h_dodds":2.7,"m_t_dodds":3.3,"m_a_dodds":2.65,"m_h_prob":0.3605861543,"m_t_prob":0.2752223889,"m_a_prob":0.3641914568,"m_h_er":-0.0264173833,"m_t_er":-0.0917661168,"m_a_er":-0.0348926395,"m_tqe_pick":"home"},"10":{"GMT_schedule":"2021-01-28T20:00:00.0000000Z","EST_schedule":"2021-01-28 15:00:00","h_team":"Tottenham","a_team":"Liverpool","m_h_odds":"+215","m_a_odds":"+117","m_t_odds":"+270","league_name":"EPL","m_h_improb":0.3174603175,"m_t_improb":0.2702702703,"m_a_improb":0.4608294931,"m_h_dodds":3.15,"m_t_dodds":3.7,"m_a_dodds":2.17,"m_h_prob":0.2927636344,"m_t_prob":0.2479557888,"m_a_prob":0.4592805769,"m_h_er":-0.0777945518,"m_t_er":-0.0825635816,"m_a_er":-0.0033611482,"m_tqe_pick":"away"},"29":{"GMT_schedule":"2021-01-29T19:30:00.0000000Z","EST_schedule":"2021-01-29 14:30:00","h_team":"VfB Stuttgart","a_team":"Mainz 05","m_h_odds":"-155","m_a_odds":"+380","m_t_odds":"+325","league_name":"Bundesliga","m_h_improb":0.6078431373,"m_t_improb":0.2352941176,"m_a_improb":0.2083333333,"m_h_dodds":1.6451612903,"m_t_dodds":4.25,"m_a_dodds":4.8,"m_h_prob":0.6018927052,"m_t_prob":0.2291580058,"m_a_prob":0.168949289,"m_h_er":-0.0097894205,"m_t_er":-0.0260784752,"m_a_er":-0.1890434129,"m_tqe_pick":"home"},"65":{"GMT_schedule":"2021-01-29T19:45:00.0000000Z","EST_schedule":"2021-01-29 14:45:00","h_team":"Torino","a_team":"Fiorentina","m_h_odds":"+175","m_a_odds":"+160","m_t_odds":"+225","league_name":"Serie-A","m_h_improb":0.3636363636,"m_t_improb":0.3076923077,"m_a_improb":0.3846153846,"m_h_dodds":2.75,"m_t_dodds":3.25,"m_a_dodds":2.6,"m_h_prob":0.3503800029,"m_t_prob":0.2783050872,"m_a_prob":0.3713149099,"m_h_er":-0.0364549921,"m_t_er":-0.0955084667,"m_a_er":-0.0345812342,"m_tqe_pick":"away"},"46":{"GMT_schedule":"2021-01-29T20:00:00.0000000Z","EST_schedule":"2021-01-29 15:00:00","h_team":"Lyon","a_team":"Bordeaux","m_h_odds":"-220","m_a_odds":"+525","m_t_odds":"+350","league_name":"Ligue-1","m_h_improb":0.6875,"m_t_improb":0.2222222222,"m_a_improb":0.16,"m_h_dodds":1.4545454545,"m_t_dodds":4.5,"m_a_dodds":6.25,"m_h_prob":0.6583912898,"m_t_prob":0.221812783,"m_a_prob":0.1197959272,"m_h_er":-0.0423399421,"m_t_er":-0.0018424767,"m_a_er":-0.2512754547,"m_tqe_pick":"tie"},"84":{"GMT_schedule":"2021-01-29T20:00:00.0000000Z","EST_schedule":"2021-01-29 15:00:00","h_team":"Valladolid","a_team":"Huesca","m_h_odds":"+125","m_a_odds":"+225","m_t_odds":"+235","league_name":"La-Liga","m_h_improb":0.4444444444,"m_t_improb":0.2985074627,"m_a_improb":0.3076923077,"m_h_dodds":2.25,"m_t_dodds":3.35,"m_a_dodds":3.25,"m_h_prob":0.4493947775,"m_t_prob":0.2722924796,"m_a_prob":0.2783127429,"m_h_er":0.0111382494,"m_t_er":-0.0878201932,"m_a_er":-0.0954835857,"m_tqe_pick":"home"},"11":{"GMT_schedule":"2021-01-30T12:30:00.0000000Z","EST_schedule":"2021-01-30 07:30:00","h_team":"Everton","a_team":"Newcastle","m_h_odds":"-200","m_a_odds":"+575","m_t_odds":"+330","league_name":"EPL","m_h_improb":0.6666666667,"m_t_improb":0.2325581395,"m_a_improb":0.1481481481,"m_h_dodds":1.5,"m_t_dodds":4.3,"m_a_dodds":6.75,"m_h_prob":0.6552819931,"m_t_prob":0.2351863875,"m_a_prob":0.1095316195,"m_h_er":-0.0170770104,"m_t_er":0.0113014662,"m_a_er":-0.2606615686,"m_tqe_pick":"tie"},"85":{"GMT_schedule":"2021-01-30T13:00:00.0000000Z","EST_schedule":"2021-01-30 08:00:00","h_team":"Eibar","a_team":"Sevilla","m_h_odds":"+300","m_a_odds":"+105","m_t_odds":"+220","league_name":"La-Liga","m_h_improb":0.25,"m_t_improb":0.3125,"m_a_improb":0.487804878,"m_h_dodds":4.0,"m_t_dodds":3.2,"m_a_dodds":2.05,"m_h_prob":0.2076518239,"m_t_prob":0.2948575907,"m_a_prob":0.4974905854,"m_h_er":-0.1693927046,"m_t_er":-0.0564557097,"m_a_er":0.0198557001,"m_tqe_pick":"away"},"66":{"GMT_schedule":"2021-01-30T14:00:00.0000000Z","EST_schedule":"2021-01-30 09:00:00","h_team":"Bologna","a_team":"AC Milan","m_h_odds":"+330","m_a_odds":"-134","m_t_odds":"+285","league_name":"Serie-A","m_h_improb":0.2325581395,"m_t_improb":0.2597402597,"m_a_improb":0.5726495726,"m_h_dodds":4.3,"m_t_dodds":3.85,"m_a_dodds":1.7462686567,"m_h_prob":0.1868574518,"m_t_prob":0.2474512912,"m_a_prob":0.565691257,"m_h_er":-0.1965129573,"m_t_er":-0.0473125291,"m_a_er":-0.0121510884,"m_tqe_pick":"away"},"31":{"GMT_schedule":"2021-01-30T14:30:00.0000000Z","EST_schedule":"2021-01-30 09:30:00","h_team":"Eintracht Frankfurt","a_team":"Hertha BSC","m_h_odds":"-118","m_a_odds":"+285","m_t_odds":"+300","league_name":"Bundesliga","m_h_improb":0.5412844037,"m_t_improb":0.25,"m_a_improb":0.2597402597,"m_h_dodds":1.8474576271,"m_t_dodds":4.0,"m_a_dodds":3.85,"m_h_prob":0.5423383036,"m_t_prob":0.2339634221,"m_a_prob":0.2236982743,"m_h_er":0.0019470354,"m_t_er":-0.0641463115,"m_a_er":-0.138761644,"m_tqe_pick":"home"},"30":{"GMT_schedule":"2021-01-30T14:30:00.0000000Z","EST_schedule":"2021-01-30 09:30:00","h_team":"1. FC Union Berlin","a_team":"Borussia M\u00f6nchengladbach","m_h_odds":"+185","m_a_odds":"+135","m_t_odds":"+265","league_name":"Bundesliga","m_h_improb":0.350877193,"m_t_improb":0.2739726027,"m_a_improb":0.4255319149,"m_h_dodds":2.85,"m_t_dodds":3.65,"m_a_dodds":2.35,"m_h_prob":0.3340138422,"m_t_prob":0.2481130458,"m_a_prob":0.417873112,"m_h_er":-0.0480605497,"m_t_er":-0.0943873829,"m_a_er":-0.0179981868,"m_tqe_pick":"away"},"33":{"GMT_schedule":"2021-01-30T14:30:00.0000000Z","EST_schedule":"2021-01-30 09:30:00","h_team":"Borussia Dortmund","a_team":"FC Augsburg","m_h_odds":"-455","m_a_odds":"+1200","m_t_odds":"+550","league_name":"Bundesliga","m_h_improb":0.8198198198,"m_t_improb":0.1538461538,"m_a_improb":0.0769230769,"m_h_dodds":1.2197802198,"m_t_dodds":6.5,"m_a_dodds":13.0,"m_h_prob":0.7919994029,"m_t_prob":0.1576779273,"m_a_prob":0.0503226698,"m_h_er":-0.0339347943,"m_t_er":0.0249065273,"m_a_er":-0.3458052924,"m_tqe_pick":"tie"},"34":{"GMT_schedule":"2021-01-30T14:30:00.0000000Z","EST_schedule":"2021-01-30 09:30:00","h_team":"Bayern Munich","a_team":"TSG Hoffenheim","m_h_odds":"-455","m_a_odds":"+1000","m_t_odds":"+620","league_name":"Bundesliga","m_h_improb":0.8198198198,"m_t_improb":0.1388888889,"m_a_improb":0.0909090909,"m_h_dodds":1.2197802198,"m_t_dodds":7.2,"m_a_dodds":11.0,"m_h_prob":0.7958376977,"m_t_prob":0.1430379956,"m_a_prob":0.0611243067,"m_h_er":-0.0292529181,"m_t_er":0.0298735682,"m_a_er":-0.3276326265,"m_tqe_pick":"tie"},"32":{"GMT_schedule":"2021-01-30T14:30:00.0000000Z","EST_schedule":"2021-01-30 09:30:00","h_team":"Werder Bremen","a_team":"FC Schalke 04","m_h_odds":"-109","m_a_odds":"+295","m_t_odds":"+255","league_name":"Bundesliga","m_h_improb":0.5215311005,"m_t_improb":0.2816901408,"m_a_improb":0.253164557,"m_h_dodds":1.9174311927,"m_t_dodds":3.55,"m_a_dodds":3.95,"m_h_prob":0.5247837965,"m_t_prob":0.2614823335,"m_a_prob":0.21373387,"m_h_er":0.0062368208,"m_t_er":-0.0717377161,"m_a_er":-0.1557512134,"m_tqe_pick":"home"},"12":{"GMT_schedule":"2021-01-30T15:00:00.0000000Z","EST_schedule":"2021-01-30 10:00:00","h_team":"Crystal Palace","a_team":"Wolves","m_h_odds":"+215","m_a_odds":"+145","m_t_odds":"+210","league_name":"EPL","m_h_improb":0.3174603175,"m_t_improb":0.3225806452,"m_a_improb":0.4081632653,"m_h_dodds":3.15,"m_t_dodds":3.1,"m_a_dodds":2.45,"m_h_prob":0.2948835806,"m_t_prob":0.2980902309,"m_a_prob":0.4070261886,"m_h_er":-0.0711167212,"m_t_er":-0.0759202843,"m_a_er":-0.002785838,"m_tqe_pick":"away"},"13":{"GMT_schedule":"2021-01-30T15:00:00.0000000Z","EST_schedule":"2021-01-30 10:00:00","h_team":"West Bromwich","a_team":"Fulham","m_h_odds":"+225","m_a_odds":"+135","m_t_odds":"+215","league_name":"EPL","m_h_improb":0.3076923077,"m_t_improb":0.3174603175,"m_a_improb":0.4255319149,"m_h_dodds":3.25,"m_t_dodds":3.15,"m_a_dodds":2.35,"m_h_prob":0.2810373772,"m_t_prob":0.2930365167,"m_a_prob":0.4259261061,"m_h_er":-0.086628524,"m_t_er":-0.0769349724,"m_a_er":0.0009263493,"m_tqe_pick":"away"},"14":{"GMT_schedule":"2021-01-30T15:00:00.0000000Z","EST_schedule":"2021-01-30 10:00:00","h_team":"Manchester City","a_team":"Sheffield United","m_h_odds":"-625","m_a_odds":"+1600","m_t_odds":"+700","league_name":"EPL","m_h_improb":0.8620689655,"m_t_improb":0.125,"m_a_improb":0.0588235294,"m_h_dodds":1.16,"m_t_dodds":8.0,"m_a_dodds":17.0,"m_h_prob":0.83635726,"m_t_prob":0.1265583354,"m_a_prob":0.0370844047,"m_h_er":-0.0298255784,"m_t_er":0.0124666831,"m_a_er":-0.3695651209,"m_tqe_pick":"tie"},"86":{"GMT_schedule":"2021-01-30T15:15:00.0000000Z","EST_schedule":"2021-01-30 10:15:00","h_team":"Real Madrid","a_team":"Levante","m_h_odds":"-265","m_a_odds":"+600","m_t_odds":"+425","league_name":"La-Liga","m_h_improb":0.7260273973,"m_t_improb":0.1904761905,"m_a_improb":0.1428571429,"m_h_dodds":1.3773584906,"m_t_dodds":5.25,"m_a_dodds":7.0,"m_h_prob":0.6997537509,"m_t_prob":0.1946970276,"m_a_prob":0.1055492215,"m_h_er":-0.0361882298,"m_t_er":0.0221593947,"m_a_er":-0.2611554495,"m_tqe_pick":"tie"},"47":{"GMT_schedule":"2021-01-30T16:00:00.0000000Z","EST_schedule":"2021-01-30 11:00:00","h_team":"Montpellier","a_team":"Lens","m_h_odds":"+145","m_a_odds":"+185","m_t_odds":"+225","league_name":"Ligue-1","m_h_improb":0.4081632653,"m_t_improb":0.3076923077,"m_a_improb":0.350877193,"m_h_dodds":2.45,"m_t_dodds":3.25,"m_a_dodds":2.85,"m_h_prob":0.3999588604,"m_t_prob":0.2743648727,"m_a_prob":0.3256762669,"m_h_er":-0.0201007921,"m_t_er":-0.1083141636,"m_a_er":-0.0718226394,"m_tqe_pick":"home"},"67":{"GMT_schedule":"2021-01-30T17:00:00.0000000Z","EST_schedule":"2021-01-30 12:00:00","h_team":"Sampdoria","a_team":"Juventus","m_h_odds":"+540","m_a_odds":"-200","m_t_odds":"+315","league_name":"Serie-A","m_h_improb":0.15625,"m_t_improb":0.2409638554,"m_a_improb":0.6666666667,"m_h_dodds":6.4,"m_t_dodds":4.15,"m_a_dodds":1.5,"m_h_prob":0.106367002,"m_t_prob":0.2412252969,"m_a_prob":0.6524077011,"m_h_er":-0.3192511875,"m_t_er":0.0010849823,"m_a_er":-0.0213884484,"m_tqe_pick":"tie"},"15":{"GMT_schedule":"2021-01-30T17:30:00.0000000Z","EST_schedule":"2021-01-30 12:30:00","h_team":"Arsenal","a_team":"Manchester United","m_h_odds":"+190","m_a_odds":"+140","m_t_odds":"+245","league_name":"EPL","m_h_improb":0.3448275862,"m_t_improb":0.2898550725,"m_a_improb":0.4166666667,"m_h_dodds":2.9,"m_t_dodds":3.45,"m_a_dodds":2.4,"m_h_prob":0.3270136917,"m_t_prob":0.2633527422,"m_a_prob":0.4096335661,"m_h_er":-0.051660294,"m_t_er":-0.0914330394,"m_a_er":-0.0168794414,"m_tqe_pick":"away"},"87":{"GMT_schedule":"2021-01-30T17:30:00.0000000Z","EST_schedule":"2021-01-30 12:30:00","h_team":"Valencia","a_team":"Elche","m_h_odds":"-159","m_a_odds":"+475","m_t_odds":"+280","league_name":"La-Liga","m_h_improb":0.6138996139,"m_t_improb":0.2631578947,"m_a_improb":0.1739130435,"m_h_dodds":1.6289308176,"m_t_dodds":3.8,"m_a_dodds":5.75,"m_h_prob":0.6096708077,"m_t_prob":0.258321992,"m_a_prob":0.1320072003,"m_h_er":-0.0068884327,"m_t_er":-0.0183764306,"m_a_er":-0.2409585981,"m_tqe_pick":"home"},"35":{"GMT_schedule":"2021-01-30T17:30:00.0000000Z","EST_schedule":"2021-01-30 12:30:00","h_team":"RB Leipzig","a_team":"Bayer Leverkusen","m_h_odds":"-125","m_a_odds":"+290","m_t_odds":"+320","league_name":"Bundesliga","m_h_improb":0.5555555556,"m_t_improb":0.2380952381,"m_a_improb":0.2564102564,"m_h_dodds":1.8,"m_t_dodds":4.2,"m_a_dodds":3.9,"m_h_prob":0.5547076409,"m_t_prob":0.2243051345,"m_a_prob":0.2209872246,"m_h_er":-0.0015262464,"m_t_er":-0.0579184352,"m_a_er":-0.138149824,"m_tqe_pick":"home"},"68":{"GMT_schedule":"2021-01-30T19:45:00.0000000Z","EST_schedule":"2021-01-30 14:45:00","h_team":"Inter","a_team":"Benevento","m_h_odds":"-435","m_a_odds":"+975","m_t_odds":"+535","league_name":"Serie-A","m_h_improb":0.8130841121,"m_t_improb":0.157480315,"m_a_improb":0.0930232558,"m_h_dodds":1.2298850575,"m_t_dodds":6.35,"m_a_dodds":10.75,"m_h_prob":0.7778844208,"m_t_prob":0.160135132,"m_a_prob":0.0619804471,"m_h_er":-0.0432915744,"m_t_er":0.0168580885,"m_a_er":-0.3337101932,"m_tqe_pick":"tie"},"16":{"GMT_schedule":"2021-01-30T20:00:00.0000000Z","EST_schedule":"2021-01-30 15:00:00","h_team":"Southampton","a_team":"Aston Villa","m_h_odds":"+140","m_a_odds":"+180","m_t_odds":"+265","league_name":"EPL","m_h_improb":0.4166666667,"m_t_improb":0.2739726027,"m_a_improb":0.3571428571,"m_h_dodds":2.4,"m_t_dodds":3.65,"m_a_dodds":2.8,"m_h_prob":0.4149286648,"m_t_prob":0.2474488963,"m_a_prob":0.3376224389,"m_h_er":-0.0041712045,"m_t_er":-0.0968115285,"m_a_er":-0.0546571711,"m_tqe_pick":"home"},"88":{"GMT_schedule":"2021-01-30T20:00:00.0000000Z","EST_schedule":"2021-01-30 15:00:00","h_team":"Villarreal","a_team":"Real Sociedad","m_h_odds":"+135","m_a_odds":"+235","m_t_odds":"+205","league_name":"La-Liga","m_h_improb":0.4255319149,"m_t_improb":0.3278688525,"m_a_improb":0.2985074627,"m_h_dodds":2.35,"m_t_dodds":3.05,"m_a_dodds":3.35,"m_h_prob":0.4313451753,"m_t_prob":0.3006480255,"m_a_prob":0.2680067992,"m_h_er":0.013661162,"m_t_er":-0.0830235222,"m_a_er":-0.1021772227,"m_tqe_pick":"home"},"48":{"GMT_schedule":"2021-01-30T20:00:00.0000000Z","EST_schedule":"2021-01-30 15:00:00","h_team":"Marseille","a_team":"Rennes","m_h_odds":"+155","m_a_odds":"+175","m_t_odds":"+220","league_name":"Ligue-1","m_h_improb":0.3921568627,"m_t_improb":0.3125,"m_a_improb":0.3636363636,"m_h_dodds":2.55,"m_t_dodds":3.2,"m_a_dodds":2.75,"m_h_prob":0.3807030619,"m_t_prob":0.27840895,"m_a_prob":0.3408879881,"m_h_er":-0.0292071921,"m_t_er":-0.10909136,"m_a_er":-0.0625580327,"m_tqe_pick":"home"},"69":{"GMT_schedule":"2021-01-31T11:30:00.0000000Z","EST_schedule":"2021-01-31 06:30:00","h_team":"Spezia","a_team":"Udinese","m_h_odds":"+270","m_a_odds":"+120","m_t_odds":"+200","league_name":"Serie-A","m_h_improb":0.2702702703,"m_t_improb":0.3333333333,"m_a_improb":0.4545454545,"m_h_dodds":3.7,"m_t_dodds":3.0,"m_a_dodds":2.2,"m_h_prob":0.2313600504,"m_t_prob":0.3096896828,"m_a_prob":0.4589502669,"m_h_er":-0.1439678136,"m_t_er":-0.0709309517,"m_a_er":0.0096905871,"m_tqe_pick":"away"},"17":{"GMT_schedule":"2021-01-31T12:00:00.0000000Z","EST_schedule":"2021-01-31 07:00:00","h_team":"Chelsea","a_team":"Burnley","m_h_odds":"-225","m_a_odds":"+650","m_t_odds":"+335","league_name":"EPL","m_h_improb":0.6923076923,"m_t_improb":0.2298850575,"m_a_improb":0.1333333333,"m_h_dodds":1.4444444444,"m_t_dodds":4.35,"m_a_dodds":7.5,"m_h_prob":0.6713182723,"m_t_prob":0.2329617503,"m_a_prob":0.0957199774,"m_h_er":-0.0303180511,"m_t_er":0.0133836136,"m_a_er":-0.2821001692,"m_tqe_pick":"tie"},"49":{"GMT_schedule":"2021-01-31T12:00:00.0000000Z","EST_schedule":"2021-01-31 07:00:00","h_team":"Nice","a_team":"Saint-\u00c9tienne","m_h_odds":"+143","m_a_odds":"+175","m_t_odds":"+250","league_name":"Ligue-1","m_h_improb":0.4115226337,"m_t_improb":0.2857142857,"m_a_improb":0.3636363636,"m_h_dodds":2.43,"m_t_dodds":3.5,"m_a_dodds":2.75,"m_h_prob":0.4039101129,"m_t_prob":0.2548260081,"m_a_prob":0.341263879,"m_h_er":-0.0184984257,"m_t_er":-0.1081089716,"m_a_er":-0.0615243328,"m_tqe_pick":"home"},"89":{"GMT_schedule":"2021-01-31T13:00:00.0000000Z","EST_schedule":"2021-01-31 08:00:00","h_team":"Getafe","a_team":"Alav\u00e9s","m_h_odds":"-112","m_a_odds":"+350","m_t_odds":"+230","league_name":"La-Liga","m_h_improb":0.5283018868,"m_t_improb":0.303030303,"m_a_improb":0.2222222222,"m_h_dodds":1.8928571429,"m_t_dodds":3.3,"m_a_dodds":4.5,"m_h_prob":0.5361602266,"m_t_prob":0.2848501269,"m_a_prob":0.1789896465,"m_h_er":0.0148747146,"m_t_er":-0.0599945813,"m_a_er":-0.1945465906,"m_tqe_pick":"home"},"71":{"GMT_schedule":"2021-01-31T14:00:00.0000000Z","EST_schedule":"2021-01-31 09:00:00","h_team":"Crotone","a_team":"Genoa","m_h_odds":"+165","m_a_odds":"+175","m_t_odds":"+215","league_name":"Serie-A","m_h_improb":0.3773584906,"m_t_improb":0.3174603175,"m_a_improb":0.3636363636,"m_h_dodds":2.65,"m_t_dodds":3.15,"m_a_dodds":2.75,"m_h_prob":0.3675711735,"m_t_prob":0.2867789696,"m_a_prob":0.3456498569,"m_h_er":-0.0259363902,"m_t_er":-0.0966462456,"m_a_er":-0.0494628936,"m_tqe_pick":"home"},"52":{"GMT_schedule":"2021-01-31T14:00:00.0000000Z","EST_schedule":"2021-01-31 09:00:00","h_team":"Lorient","a_team":"Paris SG","m_h_odds":"+900","m_a_odds":"-420","m_t_odds":"+540","league_name":"Ligue-1","m_h_improb":0.1,"m_t_improb":0.15625,"m_a_improb":0.8076923077,"m_h_dodds":10.0,"m_t_dodds":6.4,"m_a_dodds":1.2380952381,"m_h_prob":0.0589367021,"m_t_prob":0.1589750379,"m_a_prob":0.78208826,"m_h_er":-0.4106329789,"m_t_er":0.0174402426,"m_a_er":-0.0317002496,"m_tqe_pick":"tie"},"72":{"GMT_schedule":"2021-01-31T14:00:00.0000000Z","EST_schedule":"2021-01-31 09:00:00","h_team":"Cagliari","a_team":"Sassuolo","m_h_odds":"+220","m_a_odds":"+130","m_t_odds":"+220","league_name":"Serie-A","m_h_improb":0.3125,"m_t_improb":0.3125,"m_a_improb":0.4347826087,"m_h_dodds":3.2,"m_t_dodds":3.2,"m_a_dodds":2.3,"m_h_prob":0.2842867145,"m_t_prob":0.28504342,"m_a_prob":0.4306698655,"m_h_er":-0.0902825136,"m_t_er":-0.0878610559,"m_a_er":-0.0094593094,"m_tqe_pick":"away"},"53":{"GMT_schedule":"2021-01-31T14:00:00.0000000Z","EST_schedule":"2021-01-31 09:00:00","h_team":"Angers","a_team":"N\u00eemes Olympique","m_h_odds":"-143","m_a_odds":"+380","m_t_odds":"+270","league_name":"Ligue-1","m_h_improb":0.5884773663,"m_t_improb":0.2702702703,"m_a_improb":0.2083333333,"m_h_dodds":1.6993006993,"m_t_dodds":3.7,"m_a_dodds":4.8,"m_h_prob":0.5780376253,"m_t_prob":0.2570040829,"m_a_prob":0.1649582919,"m_h_er":-0.0177402592,"m_t_er":-0.0490848934,"m_a_er":-0.208200199,"m_tqe_pick":"home"},"18":{"GMT_schedule":"2021-01-31T14:00:00.0000000Z","EST_schedule":"2021-01-31 09:00:00","h_team":"Leicester City","a_team":"Leeds United","m_h_odds":"-118","m_a_odds":"+300","m_t_odds":"+290","league_name":"EPL","m_h_improb":0.5412844037,"m_t_improb":0.2564102564,"m_a_improb":0.25,"m_h_dodds":1.8474576271,"m_t_dodds":3.9,"m_a_dodds":4.0,"m_h_prob":0.5456883304,"m_t_prob":0.2414447339,"m_a_prob":0.2128669357,"m_h_er":0.008136068,"m_t_er":-0.0583655379,"m_a_er":-0.1485322571,"m_tqe_pick":"home"},"70":{"GMT_schedule":"2021-01-31T14:00:00.0000000Z","EST_schedule":"2021-01-31 09:00:00","h_team":"Atalanta","a_team":"Lazio","m_h_odds":"-120","m_a_odds":"+285","m_t_odds":"+285","league_name":"Serie-A","m_h_improb":0.5454545455,"m_t_improb":0.2597402597,"m_a_improb":0.2597402597,"m_h_dodds":1.8333333333,"m_t_dodds":3.85,"m_a_dodds":3.85,"m_h_prob":0.5386344823,"m_t_prob":0.2402607161,"m_a_prob":0.2211048016,"m_h_er":-0.0125034491,"m_t_er":-0.0749962431,"m_a_er":-0.1487465138,"m_tqe_pick":"home"},"50":{"GMT_schedule":"2021-01-31T14:00:00.0000000Z","EST_schedule":"2021-01-31 09:00:00","h_team":"Strasbourg","a_team":"Reims","m_h_odds":"+106","m_a_odds":"+290","m_t_odds":"+210","league_name":"Ligue-1","m_h_improb":0.4854368932,"m_t_improb":0.3225806452,"m_a_improb":0.2564102564,"m_h_dodds":2.06,"m_t_dodds":3.1,"m_a_dodds":3.9,"m_h_prob":0.4898267292,"m_t_prob":0.2953797793,"m_a_prob":0.2147934916,"m_h_er":0.0090430621,"m_t_er":-0.0843226843,"m_a_er":-0.1623053829,"m_tqe_pick":"home"},"51":{"GMT_schedule":"2021-01-31T14:00:00.0000000Z","EST_schedule":"2021-01-31 09:00:00","h_team":"Brest","a_team":"Metz","m_h_odds":"+128","m_a_odds":"+210","m_t_odds":"+230","league_name":"Ligue-1","m_h_improb":0.4385964912,"m_t_improb":0.303030303,"m_a_improb":0.3225806452,"m_h_dodds":2.28,"m_t_dodds":3.3,"m_a_dodds":3.1,"m_h_prob":0.4358618702,"m_t_prob":0.2717926899,"m_a_prob":0.2923454399,"m_h_er":-0.0062349359,"m_t_er":-0.1030841235,"m_a_er":-0.0937291363,"m_tqe_pick":"home"},"36":{"GMT_schedule":"2021-01-31T14:30:00.0000000Z","EST_schedule":"2021-01-31 09:30:00","h_team":"1. FC K\u00f6ln","a_team":"Arminia Bielefeld","m_h_odds":"+120","m_a_odds":"+240","m_t_odds":"+230","league_name":"Bundesliga","m_h_improb":0.4545454545,"m_t_improb":0.303030303,"m_a_improb":0.2941176471,"m_h_dodds":2.2,"m_t_dodds":3.3,"m_a_dodds":3.4,"m_h_prob":0.4609644481,"m_t_prob":0.2772374464,"m_a_prob":0.2617981054,"m_h_er":0.0141217859,"m_t_er":-0.0851164268,"m_a_er":-0.1098864415,"m_tqe_pick":"home"},"90":{"GMT_schedule":"2021-01-31T15:15:00.0000000Z","EST_schedule":"2021-01-31 10:15:00","h_team":"Cadiz","a_team":"Atl\u00e9tico Madrid","m_h_odds":"+825","m_a_odds":"-195","m_t_odds":"+250","league_name":"La-Liga","m_h_improb":0.1081081081,"m_t_improb":0.2857142857,"m_a_improb":0.6610169492,"m_h_dodds":9.25,"m_t_dodds":3.5,"m_a_dodds":1.5128205128,"m_h_prob":0.0641214436,"m_t_prob":0.2863245974,"m_a_prob":0.649553959,"m_h_er":-0.4068766467,"m_t_er":0.0021360908,"m_a_er":-0.0173414466,"m_tqe_pick":"tie"},"54":{"GMT_schedule":"2021-01-31T16:00:00.0000000Z","EST_schedule":"2021-01-31 11:00:00","h_team":"Lille","a_team":"Dijon","m_h_odds":"-250","m_a_odds":"+700","m_t_odds":"+360","league_name":"Ligue-1","m_h_improb":0.7142857143,"m_t_improb":0.2173913043,"m_a_improb":0.125,"m_h_dodds":1.4,"m_t_dodds":4.6,"m_a_dodds":8.0,"m_h_prob":0.6896200247,"m_t_prob":0.221638742,"m_a_prob":0.0887412333,"m_h_er":-0.0345319654,"m_t_er":0.0195382131,"m_a_er":-0.2900701335,"m_tqe_pick":"tie"},"19":{"GMT_schedule":"2021-01-31T16:30:00.0000000Z","EST_schedule":"2021-01-31 11:30:00","h_team":"West Ham","a_team":"Liverpool","m_h_odds":"+350","m_a_odds":"-130","m_t_odds":"+285","league_name":"EPL","m_h_improb":0.2222222222,"m_t_improb":0.2597402597,"m_a_improb":0.5652173913,"m_h_dodds":4.5,"m_t_dodds":3.85,"m_a_dodds":1.7692307692,"m_h_prob":0.1769720185,"m_t_prob":0.2519261802,"m_a_prob":0.5711018013,"m_h_er":-0.203625917,"m_t_er":-0.0300842061,"m_a_er":0.0104108792,"m_tqe_pick":"away"},"37":{"GMT_schedule":"2021-01-31T17:00:00.0000000Z","EST_schedule":"2021-01-31 12:00:00","h_team":"VfL Wolfsburg","a_team":"SC Freiburg","m_h_odds":"-106","m_a_odds":"+285","m_t_odds":"+260","league_name":"Bundesliga","m_h_improb":0.5145631068,"m_t_improb":0.2777777778,"m_a_improb":0.2597402597,"m_h_dodds":1.9433962264,"m_t_dodds":3.6,"m_a_dodds":3.85,"m_h_prob":0.5200299279,"m_t_prob":0.2579773448,"m_a_prob":0.2219927273,"m_h_er":0.0106241995,"m_t_er":-0.0712815586,"m_a_er":-0.145328,"m_tqe_pick":"home"},"73":{"GMT_schedule":"2021-01-31T17:00:00.0000000Z","EST_schedule":"2021-01-31 12:00:00","h_team":"Napoli","a_team":"Parma","m_h_odds":"-400","m_a_odds":"+1000","m_t_odds":"+480","league_name":"Serie-A","m_h_improb":0.8,"m_t_improb":0.1724137931,"m_a_improb":0.0909090909,"m_h_dodds":1.25,"m_t_dodds":5.8,"m_a_dodds":11.0,"m_h_prob":0.764058091,"m_t_prob":0.1755210147,"m_a_prob":0.0604208942,"m_h_er":-0.0449273862,"m_t_er":0.0180218855,"m_a_er":-0.3353701635,"m_tqe_pick":"tie"},"91":{"GMT_schedule":"2021-01-31T17:30:00.0000000Z","EST_schedule":"2021-01-31 12:30:00","h_team":"Granada CF","a_team":"Celta Vigo","m_h_odds":"+150","m_a_odds":"+188","m_t_odds":"+225","league_name":"La-Liga","m_h_improb":0.4,"m_t_improb":0.3076923077,"m_a_improb":0.3472222222,"m_h_dodds":2.5,"m_t_dodds":3.25,"m_a_dodds":2.88,"m_h_prob":0.3959701618,"m_t_prob":0.2782681759,"m_a_prob":0.3257616623,"m_h_er":-0.0100745956,"m_t_er":-0.0956284283,"m_a_er":-0.0618064125,"m_tqe_pick":"home"},"20":{"GMT_schedule":"2021-01-31T19:15:00.0000000Z","EST_schedule":"2021-01-31 14:15:00","h_team":"Brighton","a_team":"Tottenham","m_h_odds":"+250","m_a_odds":"+105","m_t_odds":"+265","league_name":"EPL","m_h_improb":0.2857142857,"m_t_improb":0.2739726027,"m_a_improb":0.487804878,"m_h_dodds":3.5,"m_t_dodds":3.65,"m_a_dodds":2.05,"m_h_prob":0.2532198743,"m_t_prob":0.2553540526,"m_a_prob":0.4914260732,"m_h_er":-0.1137304401,"m_t_er":-0.0679577081,"m_a_er":0.00742345,"m_tqe_pick":"away"},"74":{"GMT_schedule":"2021-01-31T19:45:00.0000000Z","EST_schedule":"2021-01-31 14:45:00","h_team":"Roma","a_team":"Hellas Verona","m_h_odds":"-182","m_a_odds":"+475","m_t_odds":"+315","league_name":"Serie-A","m_h_improb":0.6453900709,"m_t_improb":0.2409638554,"m_a_improb":0.1739130435,"m_h_dodds":1.5494505495,"m_t_dodds":4.15,"m_a_dodds":5.75,"m_h_prob":0.6291334585,"m_t_prob":0.2380270796,"m_a_prob":0.1328394619,"m_h_er":-0.025188817,"m_t_er":-0.0121876198,"m_a_er":-0.236173094,"m_tqe_pick":"tie"},"55":{"GMT_schedule":"2021-01-31T20:00:00.0000000Z","EST_schedule":"2021-01-31 15:00:00","h_team":"Nantes","a_team":"Monaco","m_h_odds":"+290","m_a_odds":"-113","m_t_odds":"+260","league_name":"Ligue-1","m_h_improb":0.2564102564,"m_t_improb":0.2777777778,"m_a_improb":0.5305164319,"m_h_dodds":3.9,"m_t_dodds":3.6,"m_a_dodds":1.8849557522,"m_h_prob":0.2140085267,"m_t_prob":0.2594637705,"m_a_prob":0.5265277028,"m_h_er":-0.165366746,"m_t_er":-0.065930426,"m_a_er":-0.0075185779,"m_tqe_pick":"away"},"92":{"GMT_schedule":"2021-01-31T20:00:00.0000000Z","EST_schedule":"2021-01-31 15:00:00","h_team":"FC Barcelona","a_team":"Athletic Club Bilbao","m_h_odds":"-278","m_a_odds":"+750","m_t_odds":"+400","league_name":"La-Liga","m_h_improb":0.7354497354,"m_t_improb":0.2,"m_a_improb":0.1176470588,"m_h_dodds":1.3597122302,"m_t_dodds":5.0,"m_a_dodds":8.5,"m_h_prob":0.7112783894,"m_t_prob":0.2057031027,"m_a_prob":0.0830185079,"m_h_er":-0.0328660749,"m_t_er":0.0285155135,"m_a_er":-0.2943426825,"m_tqe_pick":"tie"},"93":{"GMT_schedule":"2021-02-01T20:00:00.0000000Z","EST_schedule":"2021-02-01 15:00:00","h_team":"Real Betis","a_team":"Osasuna","m_h_odds":"+100","m_a_odds":"+310","m_t_odds":"+225","league_name":"La-Liga","m_h_improb":0.5,"m_t_improb":0.3076923077,"m_a_improb":0.243902439,"m_h_dodds":2.0,"m_t_dodds":3.25,"m_a_dodds":4.1,"m_h_prob":0.5103375202,"m_t_prob":0.2865736187,"m_a_prob":0.2030888611,"m_h_er":0.0206750405,"m_t_er":-0.0686357393,"m_a_er":-0.1673356696,"m_tqe_pick":"home"}}